chap_core/__init__.py
chap_core/alarms.py
chap_core/api.py
chap_core/api_types.py
chap_core/cli.py
chap_core/climate_predictor.py
chap_core/datatypes.py
chap_core/docker_helper_functions.py
chap_core/exceptions.py
chap_core/geojson.py
chap_core/geometry.py
chap_core/geoutils.py
chap_core/internal_state.py
chap_core/log_config.py
chap_core/model_spec.py
chap_core/pandas_adaptors.py
chap_core/rbased_docker.py
chap_core/training_control.py
chap_core/util.py
chap_core/validators.py
chap_core/adaptors/__init__.py
chap_core/adaptors/command_line_interface.py
chap_core/adaptors/gluonts.py
chap_core/adaptors/rest_api.py
chap_core/assessment/__init__.py
chap_core/assessment/data_representation_transforming.py
chap_core/assessment/dataset_splitting.py
chap_core/assessment/evaluation.py
chap_core/assessment/evaluator.py
chap_core/assessment/evaluator_suites.py
chap_core/assessment/flat_representations.py
chap_core/assessment/forecast.py
chap_core/assessment/metric_table.py
chap_core/assessment/prediction_evaluator.py
chap_core/assessment/representations.py
chap_core/assessment/backtest_plots/backtest_plot_1.py
chap_core/assessment/backtest_plots/sample_bias_plot.py
chap_core/assessment/backtest_plots/vega_lite_dash.py
chap_core/assessment/metrics/__init__.py
chap_core/assessment/metrics/above_truth.py
chap_core/assessment/metrics/base.py
chap_core/assessment/metrics/crps.py
chap_core/assessment/metrics/crps_norm.py
chap_core/assessment/metrics/example_metric.py
chap_core/assessment/metrics/mae.py
chap_core/assessment/metrics/peak_diff.py
chap_core/assessment/metrics/percentile_coverage.py
chap_core/assessment/metrics/rmse.py
chap_core/assessment/metrics/test_metrics.py
chap_core/cli_endpoints/__init__.py
chap_core/cli_endpoints/_common.py
chap_core/cli_endpoints/evaluate.py
chap_core/cli_endpoints/forecast.py
chap_core/cli_endpoints/init.py
chap_core/cli_endpoints/preference_learn.py
chap_core/cli_endpoints/utils.py
chap_core/climate_data/__init__.py
chap_core-1.1.4.dist-info/METADATA
chap_core-1.1.4.dist-info/WHEEL
chap_core-1.1.4.dist-info/entry_points.txt
chap_core-1.1.4.dist-info/licenses/LICENSE
chap_core-1.1.4.dist-info/RECORD
